murdock_ci/__init__.py
murdock_ci/config.py
murdock_ci/github_webhook.py
murdock_ci/jobs.py
murdock_ci/log.py
murdock_ci/murdock.py
murdock_ci/util.py
murdock_ci-0.1.6.dist-info/entry_points.txt
murdock_ci-0.1.6.dist-info/LICENSE
murdock_ci-0.1.6.dist-info/WHEEL
murdock_ci-0.1.6.dist-info/METADATA
murdock_ci-0.1.6.dist-info/RECORD
